History.rst
LICENSE.txt
MANIFEST.in
README.rst
constraints.txt
requirements.txt
setup.cfg
setup.py
bin/qirest
qiprofile_rest/__init__.py
qiprofile_rest.egg-info/PKG-INFO
qiprofile_rest.egg-info/SOURCES.txt
qiprofile_rest.egg-info/dependency_links.txt
qiprofile_rest.egg-info/requires.txt
qiprofile_rest.egg-info/top_level.txt
qiprofile_rest/server/__init__.py
qiprofile_rest/server/run.py
qiprofile_rest/server/settings.py
qiprofile_rest/server/spawn.py
qiprofile_rest/test/__init__.py
qiprofile_rest/test/helpers/__init__.py
qiprofile_rest/test/helpers/seed.py
qiprofile_rest/test/unit/__init__.py
qiprofile_rest/test/unit/test_seed.py